easing/__init__.py
easing/easing.py
easing-0.1.1.dist-info/LICENSE.txt
easing-0.1.1.dist-info/METADATA
easing-0.1.1.dist-info/WHEEL
easing-0.1.1.dist-info/top_level.txt
easing-0.1.1.dist-info/RECORD
