Metadata-Version: 2.1
Name: easing
Version: 0.1.1
Summary: Generating smooth animations in python
Home-page: https://github.com/NicholasARossi/Easing-Animations-with-Python
Author: Nicholas A. Rossi
Author-email: nicholas.rossi2@gmail.com
License: MIT
Download-URL: https://github.com/user/reponame/archive/v_011.tar.gz
Keywords: ANIMATION,SMOOTH,VISUALIZATION
Platform: UNKNOWN
Classifier: Development Status :: 3 - Alpha
Classifier: Intended Audience :: Developers
Classifier: Topic :: Software Development :: Build Tools
Classifier: License :: OSI Approved :: MIT License
Classifier: Programming Language :: Python :: 3
Classifier: Programming Language :: Python :: 3.4
Classifier: Programming Language :: Python :: 3.5
Classifier: Programming Language :: Python :: 3.6
Requires-Dist: matplotlib (>=3.0.3)
Requires-Dist: numpy (>=1.16.1)
Requires-Dist: pandas (>=0.24.1)
